playwright_stealth_plugin/__init__.py
playwright_stealth_plugin/py.typed
playwright_stealth_plugin/_javascript/chrome.app.js
playwright_stealth_plugin/_javascript/chrome.csi.js
playwright_stealth_plugin/_javascript/chrome.hairline.js
playwright_stealth_plugin/_javascript/chrome.load.times.js
playwright_stealth_plugin/_javascript/chrome.runtime.js
playwright_stealth_plugin/_javascript/generate.magic.arrays.js
playwright_stealth_plugin/_javascript/iframe.contentWindow.js
playwright_stealth_plugin/_javascript/media.codecs.js
playwright_stealth_plugin/_javascript/navigator.hardwareConcurrency.js
playwright_stealth_plugin/_javascript/navigator.languages.js
playwright_stealth_plugin/_javascript/navigator.permissions.js
playwright_stealth_plugin/_javascript/navigator.platform.js
playwright_stealth_plugin/_javascript/navigator.plugins.js
playwright_stealth_plugin/_javascript/navigator.userAgent.js
playwright_stealth_plugin/_javascript/navigator.vendor.js
playwright_stealth_plugin/_javascript/navigator.webdriver.js
playwright_stealth_plugin/_javascript/utils.js
playwright_stealth_plugin/_javascript/webgl.vendor.js
playwright_stealth_plugin/_javascript/window.outerdimensions.js
playwright_stealth_plugin/_python/async_api.py
playwright_stealth_plugin/_python/config.py
playwright_stealth_plugin/_python/sync_api.py
playwright_stealth_plugin-1.3.2.dist-info/METADATA
playwright_stealth_plugin-1.3.2.dist-info/WHEEL
playwright_stealth_plugin-1.3.2.dist-info/top_level.txt
playwright_stealth_plugin-1.3.2.dist-info/RECORD
