Metadata-Version: 2.4
Name: playwright-stealth-plugin
Version: 1.3.2
Summary: Playwright Plugin for Anti-Bot Stealth
Author-email: Abdullah Al Jaber <abdullah.0.al.0.jaber@gmail.com>
Project-URL: Source Code, https://github.com/abdullah-al-jaber/playwright-stealth-plugin
Requires-Python: >=3.10
Requires-Dist: playwright
